LICENSE
README.md
setup.cfg
setup.py
ad_leavers/__init__.py
ad_leavers/user_operations.py
ad_leavers/models/__init__.py
ad_leavers/models/core/__init__.py
ad_leavers/models/core/ad_ops.py
ad_leavers/models/core/exceptions.py
ad_leavers/models/core/object_class.py
ad_leavers/models/data_classes/__init__.py
ad_leavers/models/data_classes/user.py
ldap3_ad_leavers.egg-info/PKG-INFO
ldap3_ad_leavers.egg-info/SOURCES.txt
ldap3_ad_leavers.egg-info/dependency_links.txt
ldap3_ad_leavers.egg-info/requires.txt
ldap3_ad_leavers.egg-info/top_level.txt