Metadata-Version: 2.1
Name: ldap3-ad-leavers
Version: 1.2.0
Summary: A helper library for offboarding user from AD.
Home-page: https://github.com/mervinhemaraju/ldap3-ad-leavers
Author: Mervin Hemaraju
Author-email: th3pl4gu33@gmail.com
License: UNKNOWN
Platform: UNKNOWN
Requires-Python: >=3.7
License-File: LICENSE
